{
  "electoral_roll_2025": {
    "assembly_constituency": {
      "number": "128",
      "name": "राघोपुर",
      "reservation": "सामान्य"
    },
    "lok_sabha_constituency": {
      "number": "21",
      "name": "हाजीपुर",
      "reservation": "अ0 जा0"
    },
    "part_number": 176,
    "revision_details": {
      "year_of_revision": "2025",
      "qualification_date": "01-07-2025",
      "type_of_revision": "विशेष गहन पुनरीक्षण 2025",
      "date_of_publication": "01-08-2025",
      "electoral_roll_identity": "विशेष गहन पुनरीक्षण, 2025 के अन्तर्गत दिनांक 01-08-2025 को प्रारूप के रूप में प्रकाशित निर्वाचक सूची"
    },
    "divisions_in_part_number_and_name": [
      {
        "number": 1,
        "name": "मजलिसपुर"
      }
    ],
    "address": {
      "main_city_village": "मजलिसपुर",
      "post_office": "गोखुला",
      "police_station": "",
      "tehsil": "विदुरपुर",
      "district": "वैशाली",
      "पिन_코드": "844503"
    },
    "polling_station_details": {
      "polling_station_number_and_name": "176 - कन्या मध्य विद्यालय मजलिसपुर कमरा नं.-3 (पूर्वी भाग)",
      "polling_station_address": "कन्या मध्य विद्यालय,मजलिसपुर, कन्या मध्य विद्यालय मजलिसपुर",
      "polling_station_status": "सामान्य",
      "number_of_auxiliary_polling_stations": 0
    },
    "number_of_electors": {
      "starting_serial": {
        "number": 1
      },
      "ending_serial": {
        "number": 490
      },
      "male": 280,
      "female": 210,
      "third_gender": 0,
      "total": 490
    }
  }
}